elpis/__init__.py
elpis/codebase.py
elpis/constants.py
elpis/langgraph_agent.py
elpis/main.py
elpis/mcp_servers.py
elpis/prompts.py
elpis/tools.py
elpis/factories/__init__.py
elpis/factories/checkpointer_factory.py
elpis/factories/memory_factory.py
elpis/factories/model_factory.py
elpis/i18n/__init__.py
elpis/i18n/en.py
elpis/i18n/zh.py
elpis/ui/__init__.py
elpis/ui/graph.py
elpis/ui/graph_main.py
elpis/ui/langgraph.json
elpis_agent-0.0.9.dist-info/METADATA
elpis_agent-0.0.9.dist-info/WHEEL
elpis_agent-0.0.9.dist-info/entry_points.txt
elpis_agent-0.0.9.dist-info/licenses/LICENSE
elpis_agent-0.0.9.dist-info/RECORD
