Metadata-Version: 2.4
Name: elpis-agent
Version: 0.0.9
Summary: An agent named elpis, imitating cursor.
Author-email: dragons96 <521274311@qq.com>
License: MIT
License-File: LICENSE
Requires-Python: >=3.11
Requires-Dist: aiosqlite>=0.21.0
Requires-Dist: chardet>=5.2.0
Requires-Dist: click>=8.2.1
Requires-Dist: dotenv>=0.9.9
Requires-Dist: faiss-cpu>=1.11.0
Requires-Dist: gitignore-parser>=0.1.12
Requires-Dist: langchain-community>=0.3.24
Requires-Dist: langchain-mcp-adapters>=0.1.7
Requires-Dist: langchain[ollama,openai]>=0.3.25
Requires-Dist: langgraph-api>=0.2.45
Requires-Dist: langgraph-checkpoint-sqlite>=2.0.10
Requires-Dist: langgraph-cli>=0.2.12
Requires-Dist: langgraph>=0.4.8
Requires-Dist: mcp>=1.9.3
Requires-Dist: openai>=1.84.0
Requires-Dist: pydantic>=2.11.5
Provides-Extra: mem0
Requires-Dist: mem0ai; extra == 'mem0'
Provides-Extra: ui
Requires-Dist: langgraph-cli[inmem]>=0.2.12; extra == 'ui'
